{
    "AuxAudioDevice1": {
        "balance": 0.5,
        "deinterlace_field_order": 0,
        "deinterlace_mode": 0,
        "enabled": true,
        "flags": 0,
        "hotkeys": {
            "libobs.mute": [],
            "libobs.push-to-mute": [],
            "libobs.push-to-talk": [],
            "libobs.unmute": []
        },
        "id": "wasapi_input_capture",
        "mixers": 255,
        "monitoring_type": 0,
        "muted": true,
        "name": "Mic/Aux",
        "prev_ver": 436273153,
        "private_settings": {},
        "push-to-mute": false,
        "push-to-mute-delay": 0,
        "push-to-talk": false,
        "push-to-talk-delay": 0,
        "settings": {
            "device_id": "default"
        },
        "sync": 0,
        "versioned_id": "wasapi_input_capture",
        "volume": 1.0
    },
    "DesktopAudioDevice1": {
        "balance": 0.5,
        "deinterlace_field_order": 0,
        "deinterlace_mode": 0,
        "enabled": true,
        "flags": 0,
        "hotkeys": {
            "libobs.mute": [],
            "libobs.push-to-mute": [],
            "libobs.push-to-talk": [],
            "libobs.unmute": []
        },
        "id": "wasapi_output_capture",
        "mixers": 255,
        "monitoring_type": 0,
        "muted": true,
        "name": "Áudio do desktop",
        "prev_ver": 436273153,
        "private_settings": {},
        "push-to-mute": false,
        "push-to-mute-delay": 0,
        "push-to-talk": false,
        "push-to-talk-delay": 0,
        "settings": {
            "device_id": "default"
        },
        "sync": 0,
        "versioned_id": "wasapi_output_capture",
        "volume": 1.0
    },
    "current_program_scene": "ET52B",
    "current_scene": "ET52B",
    "current_transition": "Esmaecer",
    "groups": [],
    "modules": {
        "auto-scene-switcher": {
            "active": false,
            "interval": 300,
            "non_matching_scene": "",
            "switch_if_not_matching": false,
            "switches": []
        },
        "captions": {
            "enabled": false,
            "lang_id": 1046,
            "provider": "mssapi",
            "source": ""
        },
        "decklink_captions": {
            "source": ""
        },
        "output-timer": {
            "autoStartRecordTimer": false,
            "autoStartStreamTimer": false,
            "pauseRecordTimer": true,
            "recordTimerHours": 0,
            "recordTimerMinutes": 0,
            "recordTimerSeconds": 30,
            "streamTimerHours": 0,
            "streamTimerMinutes": 0,
            "streamTimerSeconds": 30
        },
        "scripts-tool": []
    },
    "name": "Sem nome",
    "preview_locked": false,
    "quick_transitions": [
        {
            "duration": 300,
            "fade_to_black": false,
            "hotkeys": [],
            "id": 1,
            "name": "Cortar"
        },
        {
            "duration": 300,
            "fade_to_black": false,
            "hotkeys": [],
            "id": 2,
            "name": "Esmaecer"
        },
        {
            "duration": 300,
            "fade_to_black": true,
            "hotkeys": [],
            "id": 3,
            "name": "Esmaecer"
        }
    ],
    "saved_projectors": [],
    "scaling_enabled": false,
    "scaling_level": 0,
    "scaling_off_x": 0.0,
    "scaling_off_y": 0.0,
    "scene_order": [
        {
            "name": "ET74C"
        },
        {
            "name": "ET76C"
        },
        {
            "name": "ET52B"
        }
    ],
    "sources": [
        {
            "balance": 0.5,
            "deinterlace_field_order": 0,
            "deinterlace_mode": 0,
            "enabled": true,
            "flags": 0,
            "hotkeys": {},
            "id": "text_gdiplus",
            "mixers": 0,
            "monitoring_type": 0,
            "muted": false,
            "name": "Turmas-ET74C",
            "prev_ver": 436273153,
            "private_settings": {},
            "push-to-mute": false,
            "push-to-mute-delay": 0,
            "push-to-talk": false,
            "push-to-talk-delay": 0,
            "settings": {
                "align": "center",
                "color": 4278190080,
                "font": {
                    "face": "Arial",
                    "flags": 0,
                    "size": 36,
                    "style": "Normal"
                },
                "text": "Turmas S21 e S22"
            },
            "sync": 0,
            "versioned_id": "text_gdiplus_v2",
            "volume": 1.0
        },
        {
            "balance": 0.5,
            "deinterlace_field_order": 0,
            "deinterlace_mode": 0,
            "enabled": true,
            "flags": 0,
            "hotkeys": {},
            "id": "text_gdiplus",
            "mixers": 0,
            "monitoring_type": 0,
            "muted": false,
            "name": "Nome-ET74C",
            "prev_ver": 436273153,
            "private_settings": {},
            "push-to-mute": false,
            "push-to-mute-delay": 0,
            "push-to-talk": false,
            "push-to-talk-delay": 0,
            "settings": {
                "align": "center",
                "color": 4278190080,
                "font": {
                    "face": "Arial",
                    "flags": 0,
                    "size": 48,
                    "style": "Normal"
                },
                "text": "Eletrônica 1"
            },
            "sync": 0,
            "versioned_id": "text_gdiplus_v2",
            "volume": 1.0
        },
        {
            "balance": 0.5,
            "deinterlace_field_order": 0,
            "deinterlace_mode": 0,
            "enabled": true,
            "flags": 0,
            "hotkeys": {},
            "id": "image_source",
            "mixers": 0,
            "monitoring_type": 0,
            "muted": false,
            "name": "ET74C-Background",
            "prev_ver": 436273153,
            "private_settings": {},
            "push-to-mute": false,
            "push-to-mute-delay": 0,
            "push-to-talk": false,
            "push-to-talk-delay": 0,
            "settings": {
                "file": "E:/Dropbox/UTFPR/APNP/Emblemas/APNP-Background.png"
            },
            "sync": 0,
            "versioned_id": "image_source",
            "volume": 1.0
        },
        {
            "balance": 0.5,
            "deinterlace_field_order": 0,
            "deinterlace_mode": 0,
            "enabled": true,
            "flags": 0,
            "hotkeys": {},
            "id": "image_source",
            "mixers": 0,
            "monitoring_type": 0,
            "muted": false,
            "name": "ET76C-Background",
            "prev_ver": 436273153,
            "private_settings": {},
            "push-to-mute": false,
            "push-to-mute-delay": 0,
            "push-to-talk": false,
            "push-to-talk-delay": 0,
            "settings": {
                "file": "E:/Dropbox/UTFPR/APNP/Emblemas/APNP-Background.png"
            },
            "sync": 0,
            "versioned_id": "image_source",
            "volume": 1.0
        },
        {
            "balance": 0.5,
            "deinterlace_field_order": 0,
            "deinterlace_mode": 0,
            "enabled": true,
            "flags": 0,
            "hotkeys": {},
            "id": "image_source",
            "mixers": 0,
            "monitoring_type": 0,
            "muted": false,
            "name": "ET52B-Background",
            "prev_ver": 436273153,
            "private_settings": {},
            "push-to-mute": false,
            "push-to-mute-delay": 0,
            "push-to-talk": false,
            "push-to-talk-delay": 0,
            "settings": {
                "file": "E:/Dropbox/UTFPR/APNP/Emblemas/APNP-Background.png"
            },
            "sync": 0,
            "versioned_id": "image_source",
            "volume": 1.0
        },
        {
            "balance": 0.5,
            "deinterlace_field_order": 0,
            "deinterlace_mode": 0,
            "enabled": true,
            "flags": 0,
            "hotkeys": {},
            "id": "text_gdiplus",
            "mixers": 0,
            "monitoring_type": 0,
            "muted": false,
            "name": "Descrição-ET74C",
            "prev_ver": 436273153,
            "private_settings": {},
            "push-to-mute": false,
            "push-to-mute-delay": 0,
            "push-to-talk": false,
            "push-to-talk-delay": 0,
            "settings": {
                "align": "center",
                "color": 4278190080,
                "font": {
                    "face": "Arial",
                    "flags": 0,
                    "size": 28,
                    "style": "Normal"
                },
                "text": "Identificação da\nfuncionalidades de circuitos\n\nAmplificador de audio;\nSensor bidirecional de corrente;\nFiltro de segunda ordem;\nGerador de referência de tensão;\nAmplificador de Transimpedância\n para receptores optoeletrônicos;\nDetector de pico;\nEntre outros...\nSimulação no LTspice;"
            },
            "sync": 0,
            "versioned_id": "text_gdiplus_v2",
            "volume": 1.0
        },
        {
            "balance": 0.5,
            "deinterlace_field_order": 0,
            "deinterlace_mode": 0,
            "enabled": true,
            "flags": 0,
            "hotkeys": {},
            "id": "text_gdiplus",
            "mixers": 0,
            "monitoring_type": 0,
            "muted": false,
            "name": "Descrição-ET52B",
            "prev_ver": 436273153,
            "private_settings": {},
            "push-to-mute": false,
            "push-to-mute-delay": 0,
            "push-to-talk": false,
            "push-to-talk-delay": 0,
            "settings": {
                "align": "center",
                "color": 4278190080,
                "font": {
                    "face": "Arial",
                    "flags": 0,
                    "size": 28,
                    "style": "Normal"
                },
                "text": "Circuitos osciladores \ne NE555\n\nConceitos iniciais;\nOscilador por comparador\nde histerese;\nOscilador astável com TBJs;\nNE555 no modo astável;\nSimulação no LTspice;"
            },
            "sync": 0,
            "versioned_id": "text_gdiplus_v2",
            "volume": 1.0
        },
        {
            "balance": 0.5,
            "deinterlace_field_order": 0,
            "deinterlace_mode": 0,
            "enabled": true,
            "flags": 0,
            "hotkeys": {},
            "id": "text_gdiplus",
            "mixers": 0,
            "monitoring_type": 0,
            "muted": false,
            "name": "Data-ET76C",
            "prev_ver": 436273153,
            "private_settings": {},
            "push-to-mute": false,
            "push-to-mute-delay": 0,
            "push-to-talk": false,
            "push-to-talk-delay": 0,
            "settings": {
                "align": "center",
                "color": 4278190080,
                "font": {
                    "face": "Arial",
                    "flags": 0,
                    "size": 48,
                    "style": "Normal"
                },
                "text": "AS-21 2020.2\n11/05/2021"
            },
            "sync": 0,
            "versioned_id": "text_gdiplus_v2",
            "volume": 1.0
        },
        {
            "balance": 0.5,
            "deinterlace_field_order": 0,
            "deinterlace_mode": 0,
            "enabled": true,
            "flags": 0,
            "hotkeys": {},
            "id": "text_gdiplus",
            "mixers": 0,
            "monitoring_type": 0,
            "muted": false,
            "name": "Data-ET74C",
            "prev_ver": 436273153,
            "private_settings": {},
            "push-to-mute": false,
            "push-to-mute-delay": 0,
            "push-to-talk": false,
            "push-to-talk-delay": 0,
            "settings": {
                "align": "center",
                "color": 4278190080,
                "font": {
                    "face": "Arial",
                    "flags": 0,
                    "size": 48,
                    "style": "Normal"
                },
                "text": "AS-22 2020.2\n12/05/2021"
            },
            "sync": 0,
            "versioned_id": "text_gdiplus_v2",
            "volume": 1.0
        },
        {
            "balance": 0.5,
            "deinterlace_field_order": 0,
            "deinterlace_mode": 0,
            "enabled": true,
            "flags": 0,
            "hotkeys": {},
            "id": "text_gdiplus",
            "mixers": 0,
            "monitoring_type": 0,
            "muted": false,
            "name": "Data-ET52B",
            "prev_ver": 436273153,
            "private_settings": {},
            "push-to-mute": false,
            "push-to-mute-delay": 0,
            "push-to-talk": false,
            "push-to-talk-delay": 0,
            "settings": {
                "align": "center",
                "color": 4278190080,
                "font": {
                    "face": "Arial",
                    "flags": 0,
                    "size": 48,
                    "style": "Normal"
                },
                "text": "AS-12 2020.2\n18/05/2021"
            },
            "sync": 0,
            "versioned_id": "text_gdiplus_v2",
            "volume": 1.0
        },
        {
            "balance": 0.5,
            "deinterlace_field_order": 0,
            "deinterlace_mode": 0,
            "enabled": true,
            "flags": 0,
            "hotkeys": {},
            "id": "image_source",
            "mixers": 0,
            "monitoring_type": 0,
            "muted": false,
            "name": "APNP-ET74C-Logo",
            "prev_ver": 436273153,
            "private_settings": {},
            "push-to-mute": false,
            "push-to-mute-delay": 0,
            "push-to-talk": false,
            "push-to-talk-delay": 0,
            "settings": {
                "file": "E:/Dropbox/UTFPR/APNP/Emblemas/APNP-ET74C.png"
            },
            "sync": 0,
            "versioned_id": "image_source",
            "volume": 1.0
        },
        {
            "balance": 0.5,
            "deinterlace_field_order": 0,
            "deinterlace_mode": 0,
            "enabled": true,
            "flags": 0,
            "hotkeys": {},
            "id": "image_source",
            "mixers": 0,
            "monitoring_type": 0,
            "muted": false,
            "name": "APNP-ET52B-Logo",
            "prev_ver": 436273153,
            "private_settings": {},
            "push-to-mute": false,
            "push-to-mute-delay": 0,
            "push-to-talk": false,
            "push-to-talk-delay": 0,
            "settings": {
                "file": "E:/Dropbox/UTFPR/APNP/Emblemas/APNP-ET52B.png"
            },
            "sync": 0,
            "versioned_id": "image_source",
            "volume": 1.0
        },
        {
            "balance": 0.5,
            "deinterlace_field_order": 0,
            "deinterlace_mode": 0,
            "enabled": true,
            "flags": 0,
            "hotkeys": {},
            "id": "text_gdiplus",
            "mixers": 0,
            "monitoring_type": 0,
            "muted": false,
            "name": "Descrição",
            "prev_ver": 436273153,
            "private_settings": {},
            "push-to-mute": false,
            "push-to-mute-delay": 0,
            "push-to-talk": false,
            "push-to-talk-delay": 0,
            "settings": {
                "align": "center",
                "color": 4278190080,
                "font": {
                    "face": "Arial",
                    "flags": 0,
                    "size": 28,
                    "style": "Normal"
                },
                "text": "Conversor CC-CC Boost\nModelagem em espaço de estados \n\nModo de condução contínua;\nProjeto no MATLAB;\nVerificação do modelo;\nProjeto do controlador;\nSimulação no PSIM;"
            },
            "sync": 0,
            "versioned_id": "text_gdiplus_v2",
            "volume": 1.0
        },
        {
            "balance": 0.5,
            "deinterlace_field_order": 0,
            "deinterlace_mode": 0,
            "enabled": true,
            "flags": 0,
            "hotkeys": {},
            "id": "image_source",
            "mixers": 0,
            "monitoring_type": 0,
            "muted": false,
            "name": "APNP-ET76C-Logo",
            "prev_ver": 436273153,
            "private_settings": {},
            "push-to-mute": false,
            "push-to-mute-delay": 0,
            "push-to-talk": false,
            "push-to-talk-delay": 0,
            "settings": {
                "file": "E:/Dropbox/UTFPR/APNP/Emblemas/APNP-ET76C.png"
            },
            "sync": 0,
            "versioned_id": "image_source",
            "volume": 1.0
        },
        {
            "balance": 0.5,
            "deinterlace_field_order": 0,
            "deinterlace_mode": 0,
            "enabled": true,
            "flags": 0,
            "hotkeys": {
                "OBSBasic.SelectScene": [],
                "libobs.hide_scene_item.APNP-ET76C-Logo": [],
                "libobs.hide_scene_item.Data-ET76C": [],
                "libobs.hide_scene_item.Descrição": [],
                "libobs.hide_scene_item.ET76C-Background": [],
                "libobs.hide_scene_item.Hora": [],
                "libobs.hide_scene_item.Navegador ET76C": [],
                "libobs.hide_scene_item.Nome-ET76C": [],
                "libobs.hide_scene_item.Turmas-ET76C": [],
                "libobs.show_scene_item.APNP-ET76C-Logo": [],
                "libobs.show_scene_item.Data-ET76C": [],
                "libobs.show_scene_item.Descrição": [],
                "libobs.show_scene_item.ET76C-Background": [],
                "libobs.show_scene_item.Hora": [],
                "libobs.show_scene_item.Navegador ET76C": [],
                "libobs.show_scene_item.Nome-ET76C": [],
                "libobs.show_scene_item.Turmas-ET76C": []
            },
            "id": "scene",
            "mixers": 0,
            "monitoring_type": 0,
            "muted": false,
            "name": "ET76C",
            "prev_ver": 436273153,
            "private_settings": {},
            "push-to-mute": false,
            "push-to-mute-delay": 0,
            "push-to-talk": false,
            "push-to-talk-delay": 0,
            "settings": {
                "custom_size": false,
                "id_counter": 14,
                "items": [
                    {
                        "align": 5,
                        "bounds": {
                            "x": 0.0,
                            "y": 0.0
                        },
                        "bounds_align": 0,
                        "bounds_type": 0,
                        "crop_bottom": 0,
                        "crop_left": 0,
                        "crop_right": 0,
                        "crop_top": 0,
                        "group_item_backup": false,
                        "id": 11,
                        "locked": true,
                        "name": "ET76C-Background",
                        "pos": {
                            "x": 0.0,
                            "y": 0.0
                        },
                        "private_settings": {},
                        "rot": 0.0,
                        "scale": {
                            "x": 1.0,
                            "y": 1.0
                        },
                        "scale_filter": "disable",
                        "visible": true
                    },
                    {
                        "align": 5,
                        "bounds": {
                            "x": 0.0,
                            "y": 0.0
                        },
                        "bounds_align": 0,
                        "bounds_type": 0,
                        "crop_bottom": 0,
                        "crop_left": 0,
                        "crop_right": 0,
                        "crop_top": 0,
                        "group_item_backup": false,
                        "id": 2,
                        "locked": true,
                        "name": "Navegador ET76C",
                        "pos": {
                            "x": 65.0,
                            "y": -97.0
                        },
                        "private_settings": {},
                        "rot": 0.0,
                        "scale": {
                            "x": 1.1520832777023315,
                            "y": 1.1518518924713135
                        },
                        "scale_filter": "disable",
                        "visible": true
                    },
                    {
                        "align": 5,
                        "bounds": {
                            "x": 0.0,
                            "y": 0.0
                        },
                        "bounds_align": 0,
                        "bounds_type": 0,
                        "crop_bottom": 0,
                        "crop_left": 0,
                        "crop_right": 0,
                        "crop_top": 0,
                        "group_item_backup": false,
                        "id": 5,
                        "locked": true,
                        "name": "APNP-ET76C-Logo",
                        "pos": {
                            "x": 38.0,
                            "y": 31.0
                        },
                        "private_settings": {},
                        "rot": 0.0,
                        "scale": {
                            "x": 0.3903394341468811,
                            "y": 0.3903394341468811
                        },
                        "scale_filter": "disable",
                        "visible": true
                    },
                    {
                        "align": 5,
                        "bounds": {
                            "x": 0.0,
                            "y": 0.0
                        },
                        "bounds_align": 0,
                        "bounds_type": 0,
                        "crop_bottom": 0,
                        "crop_left": 0,
                        "crop_right": 0,
                        "crop_top": 0,
                        "group_item_backup": false,
                        "id": 9,
                        "locked": true,
                        "name": "Descrição",
                        "pos": {
                            "x": 0.0,
                            "y": 530.0
                        },
                        "private_settings": {},
                        "rot": 0.0,
                        "scale": {
                            "x": 1.0264900922775269,
                            "y": 1.0267379283905029
                        },
                        "scale_filter": "disable",
                        "visible": true
                    },
                    {
                        "align": 5,
                        "bounds": {
                            "x": 0.0,
                            "y": 0.0
                        },
                        "bounds_align": 0,
                        "bounds_type": 0,
                        "crop_bottom": 0,
                        "crop_left": 0,
                        "crop_right": 0,
                        "crop_top": 0,
                        "group_item_backup": false,
                        "id": 10,
                        "locked": true,
                        "name": "Data-ET76C",
                        "pos": {
                            "x": 49.0,
                            "y": 943.0
                        },
                        "private_settings": {},
                        "rot": 0.0,
                        "scale": {
                            "x": 1.0,
                            "y": 1.0
                        },
                        "scale_filter": "disable",
                        "visible": true
                    },
                    {
                        "align": 5,
                        "bounds": {
                            "x": 0.0,
                            "y": 0.0
                        },
                        "bounds_align": 0,
                        "bounds_type": 0,
                        "crop_bottom": 0,
                        "crop_left": 0,
                        "crop_right": 0,
                        "crop_top": 0,
                        "group_item_backup": false,
                        "id": 12,
                        "locked": true,
                        "name": "Nome-ET76C",
                        "pos": {
                            "x": 46.0,
                            "y": 330.0
                        },
                        "private_settings": {},
                        "rot": 0.0,
                        "scale": {
                            "x": 1.0,
                            "y": 1.0
                        },
                        "scale_filter": "disable",
                        "visible": true
                    },
                    {
                        "align": 5,
                        "bounds": {
                            "x": 0.0,
                            "y": 0.0
                        },
                        "bounds_align": 0,
                        "bounds_type": 0,
                        "crop_bottom": 0,
                        "crop_left": 0,
                        "crop_right": 0,
                        "crop_top": 0,
                        "group_item_backup": false,
                        "id": 13,
                        "locked": true,
                        "name": "Turmas-ET76C",
                        "pos": {
                            "x": 96.0,
                            "y": 456.0
                        },
                        "private_settings": {},
                        "rot": 0.0,
                        "scale": {
                            "x": 1.0,
                            "y": 1.0
                        },
                        "scale_filter": "disable",
                        "visible": true
                    },
                    {
                        "align": 5,
                        "bounds": {
                            "x": 0.0,
                            "y": 0.0
                        },
                        "bounds_align": 0,
                        "bounds_type": 0,
                        "crop_bottom": 0,
                        "crop_left": 0,
                        "crop_right": 0,
                        "crop_top": 0,
                        "group_item_backup": false,
                        "id": 14,
                        "locked": true,
                        "name": "Hora",
                        "pos": {
                            "x": 1769.0,
                            "y": -31.0
                        },
                        "private_settings": {},
                        "rot": 0.0,
                        "scale": {
                            "x": 0.1887499988079071,
                            "y": 0.18833333253860474
                        },
                        "scale_filter": "disable",
                        "visible": true
                    }
                ]
            },
            "sync": 0,
            "versioned_id": "scene",
            "volume": 1.0
        },
        {
            "balance": 0.5,
            "deinterlace_field_order": 0,
            "deinterlace_mode": 0,
            "enabled": true,
            "flags": 0,
            "hotkeys": {
                "OBSBasic.SelectScene": [],
                "libobs.hide_scene_item.APNP-ET74C-Logo": [],
                "libobs.hide_scene_item.Data-ET74C": [],
                "libobs.hide_scene_item.Descrição-ET74C": [],
                "libobs.hide_scene_item.ET74C-Background": [],
                "libobs.hide_scene_item.Hora": [],
                "libobs.hide_scene_item.Navegador ET74C": [],
                "libobs.hide_scene_item.Nome-ET74C": [],
                "libobs.hide_scene_item.Turmas-ET74C": [],
                "libobs.show_scene_item.APNP-ET74C-Logo": [],
                "libobs.show_scene_item.Data-ET74C": [],
                "libobs.show_scene_item.Descrição-ET74C": [],
                "libobs.show_scene_item.ET74C-Background": [],
                "libobs.show_scene_item.Hora": [],
                "libobs.show_scene_item.Navegador ET74C": [],
                "libobs.show_scene_item.Nome-ET74C": [],
                "libobs.show_scene_item.Turmas-ET74C": []
            },
            "id": "scene",
            "mixers": 0,
            "monitoring_type": 0,
            "muted": false,
            "name": "ET74C",
            "prev_ver": 436273153,
            "private_settings": {},
            "push-to-mute": false,
            "push-to-mute-delay": 0,
            "push-to-talk": false,
            "push-to-talk-delay": 0,
            "settings": {
                "custom_size": false,
                "id_counter": 11,
                "items": [
                    {
                        "align": 5,
                        "bounds": {
                            "x": 0.0,
                            "y": 0.0
                        },
                        "bounds_align": 0,
                        "bounds_type": 0,
                        "crop_bottom": 0,
                        "crop_left": 0,
                        "crop_right": 0,
                        "crop_top": 0,
                        "group_item_backup": false,
                        "id": 5,
                        "locked": true,
                        "name": "ET74C-Background",
                        "pos": {
                            "x": 0.0,
                            "y": 0.0
                        },
                        "private_settings": {},
                        "rot": 0.0,
                        "scale": {
                            "x": 1.0,
                            "y": 1.0
                        },
                        "scale_filter": "disable",
                        "visible": true
                    },
                    {
                        "align": 5,
                        "bounds": {
                            "x": 0.0,
                            "y": 0.0
                        },
                        "bounds_align": 0,
                        "bounds_type": 0,
                        "crop_bottom": 0,
                        "crop_left": 0,
                        "crop_right": 0,
                        "crop_top": 0,
                        "group_item_backup": false,
                        "id": 1,
                        "locked": true,
                        "name": "Navegador ET74C",
                        "pos": {
                            "x": 49.0,
                            "y": -106.0
                        },
                        "private_settings": {},
                        "rot": 0.0,
                        "scale": {
                            "x": 1.1671874523162842,
                            "y": 1.1675926446914673
                        },
                        "scale_filter": "disable",
                        "visible": true
                    },
                    {
                        "align": 5,
                        "bounds": {
                            "x": 0.0,
                            "y": 0.0
                        },
                        "bounds_align": 0,
                        "bounds_type": 0,
                        "crop_bottom": 0,
                        "crop_left": 0,
                        "crop_right": 0,
                        "crop_top": 0,
                        "group_item_backup": false,
                        "id": 2,
                        "locked": true,
                        "name": "APNP-ET74C-Logo",
                        "pos": {
                            "x": 30.0,
                            "y": 30.0
                        },
                        "private_settings": {},
                        "rot": 0.0,
                        "scale": {
                            "x": 0.38250651955604553,
                            "y": 0.38250651955604553
                        },
                        "scale_filter": "disable",
                        "visible": true
                    },
                    {
                        "align": 5,
                        "bounds": {
                            "x": 0.0,
                            "y": 0.0
                        },
                        "bounds_align": 0,
                        "bounds_type": 0,
                        "crop_bottom": 0,
                        "crop_left": 0,
                        "crop_right": 0,
                        "crop_top": 0,
                        "group_item_backup": false,
                        "id": 3,
                        "locked": true,
                        "name": "Data-ET74C",
                        "pos": {
                            "x": 39.0,
                            "y": 937.0
                        },
                        "private_settings": {},
                        "rot": 0.0,
                        "scale": {
                            "x": 1.0,
                            "y": 1.0
                        },
                        "scale_filter": "disable",
                        "visible": true
                    },
                    {
                        "align": 5,
                        "bounds": {
                            "x": 0.0,
                            "y": 0.0
                        },
                        "bounds_align": 0,
                        "bounds_type": 0,
                        "crop_bottom": 0,
                        "crop_left": 0,
                        "crop_right": 0,
                        "crop_top": 0,
                        "group_item_backup": false,
                        "id": 4,
                        "locked": true,
                        "name": "Descrição-ET74C",
                        "pos": {
                            "x": 0.0,
                            "y": 499.0
                        },
                        "private_settings": {},
                        "rot": 0.0,
                        "scale": {
                            "x": 1.0,
                            "y": 1.0
                        },
                        "scale_filter": "disable",
                        "visible": true
                    },
                    {
                        "align": 5,
                        "bounds": {
                            "x": 0.0,
                            "y": 0.0
                        },
                        "bounds_align": 0,
                        "bounds_type": 0,
                        "crop_bottom": 0,
                        "crop_left": 0,
                        "crop_right": 0,
                        "crop_top": 0,
                        "group_item_backup": false,
                        "id": 6,
                        "locked": true,
                        "name": "Nome-ET74C",
                        "pos": {
                            "x": 57.0,
                            "y": 345.0
                        },
                        "private_settings": {},
                        "rot": 0.0,
                        "scale": {
                            "x": 1.0,
                            "y": 1.0
                        },
                        "scale_filter": "disable",
                        "visible": true
                    },
                    {
                        "align": 5,
                        "bounds": {
                            "x": 0.0,
                            "y": 0.0
                        },
                        "bounds_align": 0,
                        "bounds_type": 0,
                        "crop_bottom": 0,
                        "crop_left": 0,
                        "crop_right": 0,
                        "crop_top": 0,
                        "group_item_backup": false,
                        "id": 7,
                        "locked": true,
                        "name": "Turmas-ET74C",
                        "pos": {
                            "x": 34.0,
                            "y": 393.0
                        },
                        "private_settings": {},
                        "rot": 0.0,
                        "scale": {
                            "x": 1.0,
                            "y": 1.0
                        },
                        "scale_filter": "disable",
                        "visible": true
                    },
                    {
                        "align": 5,
                        "bounds": {
                            "x": 0.0,
                            "y": 0.0
                        },
                        "bounds_align": 0,
                        "bounds_type": 0,
                        "crop_bottom": 0,
                        "crop_left": 0,
                        "crop_right": 0,
                        "crop_top": 0,
                        "group_item_backup": false,
                        "id": 11,
                        "locked": true,
                        "name": "Hora",
                        "pos": {
                            "x": 1777.0,
                            "y": -31.0
                        },
                        "private_settings": {},
                        "rot": 0.0,
                        "scale": {
                            "x": 0.17874999344348907,
                            "y": 0.17833332717418671
                        },
                        "scale_filter": "disable",
                        "visible": true
                    }
                ]
            },
            "sync": 0,
            "versioned_id": "scene",
            "volume": 1.0
        },
        {
            "balance": 0.5,
            "deinterlace_field_order": 0,
            "deinterlace_mode": 0,
            "enabled": true,
            "flags": 0,
            "hotkeys": {
                "OBSBasic.SelectScene": [],
                "libobs.hide_scene_item.APNP-ET52B-Logo": [],
                "libobs.hide_scene_item.Data-ET52B": [],
                "libobs.hide_scene_item.Descrição-ET52B": [],
                "libobs.hide_scene_item.ET52B-Background": [],
                "libobs.hide_scene_item.Hora": [],
                "libobs.hide_scene_item.Navegador ET52B": [],
                "libobs.hide_scene_item.Nome-ET52B": [],
                "libobs.hide_scene_item.Turma-ET52B": [],
                "libobs.show_scene_item.APNP-ET52B-Logo": [],
                "libobs.show_scene_item.Data-ET52B": [],
                "libobs.show_scene_item.Descrição-ET52B": [],
                "libobs.show_scene_item.ET52B-Background": [],
                "libobs.show_scene_item.Hora": [],
                "libobs.show_scene_item.Navegador ET52B": [],
                "libobs.show_scene_item.Nome-ET52B": [],
                "libobs.show_scene_item.Turma-ET52B": []
            },
            "id": "scene",
            "mixers": 0,
            "monitoring_type": 0,
            "muted": false,
            "name": "ET52B",
            "prev_ver": 436273153,
            "private_settings": {},
            "push-to-mute": false,
            "push-to-mute-delay": 0,
            "push-to-talk": false,
            "push-to-talk-delay": 0,
            "settings": {
                "custom_size": false,
                "id_counter": 8,
                "items": [
                    {
                        "align": 5,
                        "bounds": {
                            "x": 0.0,
                            "y": 0.0
                        },
                        "bounds_align": 0,
                        "bounds_type": 0,
                        "crop_bottom": 0,
                        "crop_left": 0,
                        "crop_right": 0,
                        "crop_top": 0,
                        "group_item_backup": false,
                        "id": 5,
                        "locked": true,
                        "name": "ET52B-Background",
                        "pos": {
                            "x": 0.0,
                            "y": 0.0
                        },
                        "private_settings": {},
                        "rot": 0.0,
                        "scale": {
                            "x": 1.0,
                            "y": 1.0
                        },
                        "scale_filter": "disable",
                        "visible": true
                    },
                    {
                        "align": 5,
                        "bounds": {
                            "x": 0.0,
                            "y": 0.0
                        },
                        "bounds_align": 0,
                        "bounds_type": 0,
                        "crop_bottom": 0,
                        "crop_left": 0,
                        "crop_right": 0,
                        "crop_top": 0,
                        "group_item_backup": false,
                        "id": 1,
                        "locked": true,
                        "name": "Navegador ET52B",
                        "pos": {
                            "x": 49.0,
                            "y": -108.0
                        },
                        "private_settings": {},
                        "rot": 0.0,
                        "scale": {
                            "x": 1.1604167222976685,
                            "y": 1.1601852178573608
                        },
                        "scale_filter": "disable",
                        "visible": true
                    },
                    {
                        "align": 5,
                        "bounds": {
                            "x": 0.0,
                            "y": 0.0
                        },
                        "bounds_align": 0,
                        "bounds_type": 0,
                        "crop_bottom": 0,
                        "crop_left": 0,
                        "crop_right": 0,
                        "crop_top": 0,
                        "group_item_backup": false,
                        "id": 2,
                        "locked": false,
                        "name": "APNP-ET52B-Logo",
                        "pos": {
                            "x": 25.0,
                            "y": 30.0
                        },
                        "private_settings": {},
                        "rot": 0.0,
                        "scale": {
                            "x": 0.38903394341468811,
                            "y": 0.38903394341468811
                        },
                        "scale_filter": "disable",
                        "visible": true
                    },
                    {
                        "align": 5,
                        "bounds": {
                            "x": 0.0,
                            "y": 0.0
                        },
                        "bounds_align": 0,
                        "bounds_type": 0,
                        "crop_bottom": 0,
                        "crop_left": 0,
                        "crop_right": 0,
                        "crop_top": 0,
                        "group_item_backup": false,
                        "id": 3,
                        "locked": false,
                        "name": "Data-ET52B",
                        "pos": {
                            "x": 26.0,
                            "y": 939.0
                        },
                        "private_settings": {},
                        "rot": 0.0,
                        "scale": {
                            "x": 1.0,
                            "y": 1.0
                        },
                        "scale_filter": "disable",
                        "visible": true
                    },
                    {
                        "align": 5,
                        "bounds": {
                            "x": 0.0,
                            "y": 0.0
                        },
                        "bounds_align": 0,
                        "bounds_type": 0,
                        "crop_bottom": 0,
                        "crop_left": 0,
                        "crop_right": 0,
                        "crop_top": 0,
                        "group_item_backup": false,
                        "id": 4,
                        "locked": false,
                        "name": "Descrição-ET52B",
                        "pos": {
                            "x": 0.0,
                            "y": 491.0
                        },
                        "private_settings": {},
                        "rot": 0.0,
                        "scale": {
                            "x": 0.8919597864151001,
                            "y": 0.89304810762405396
                        },
                        "scale_filter": "disable",
                        "visible": true
                    },
                    {
                        "align": 5,
                        "bounds": {
                            "x": 0.0,
                            "y": 0.0
                        },
                        "bounds_align": 0,
                        "bounds_type": 0,
                        "crop_bottom": 0,
                        "crop_left": 0,
                        "crop_right": 0,
                        "crop_top": 0,
                        "group_item_backup": false,
                        "id": 6,
                        "locked": false,
                        "name": "Turma-ET52B",
                        "pos": {
                            "x": 79.0,
                            "y": 411.0
                        },
                        "private_settings": {},
                        "rot": 0.0,
                        "scale": {
                            "x": 1.0,
                            "y": 1.0
                        },
                        "scale_filter": "disable",
                        "visible": true
                    },
                    {
                        "align": 5,
                        "bounds": {
                            "x": 0.0,
                            "y": 0.0
                        },
                        "bounds_align": 0,
                        "bounds_type": 0,
                        "crop_bottom": 0,
                        "crop_left": 0,
                        "crop_right": 0,
                        "crop_top": 0,
                        "group_item_backup": false,
                        "id": 7,
                        "locked": false,
                        "name": "Nome-ET52B",
                        "pos": {
                            "x": 20.0,
                            "y": 375.0
                        },
                        "private_settings": {},
                        "rot": 0.0,
                        "scale": {
                            "x": 1.0,
                            "y": 1.0
                        },
                        "scale_filter": "disable",
                        "visible": true
                    },
                    {
                        "align": 5,
                        "bounds": {
                            "x": 0.0,
                            "y": 0.0
                        },
                        "bounds_align": 0,
                        "bounds_type": 0,
                        "crop_bottom": 0,
                        "crop_left": 0,
                        "crop_right": 0,
                        "crop_top": 0,
                        "group_item_backup": false,
                        "id": 8,
                        "locked": true,
                        "name": "Hora",
                        "pos": {
                            "x": 1783.0,
                            "y": -33.0
                        },
                        "private_settings": {},
                        "rot": 0.0,
                        "scale": {
                            "x": 0.17125000059604645,
                            "y": 0.17166666686534882
                        },
                        "scale_filter": "disable",
                        "visible": true
                    }
                ]
            },
            "sync": 0,
            "versioned_id": "scene",
            "volume": 1.0
        },
        {
            "balance": 0.5,
            "deinterlace_field_order": 0,
            "deinterlace_mode": 0,
            "enabled": true,
            "flags": 0,
            "hotkeys": {
                "libobs.mute": [],
                "libobs.push-to-mute": [],
                "libobs.push-to-talk": [],
                "libobs.unmute": []
            },
            "id": "browser_source",
            "mixers": 255,
            "monitoring_type": 0,
            "muted": false,
            "name": "Navegador ET76C",
            "prev_ver": 436273153,
            "private_settings": {},
            "push-to-mute": false,
            "push-to-mute-delay": 0,
            "push-to-talk": false,
            "push-to-talk-delay": 0,
            "settings": {
                "height": 1080,
                "reroute_audio": true,
                "url": "https://moodleconf.ct.utfpr.edu.br/b/adr-xwm-pbu-tbd",
                "width": 1920
            },
            "sync": 0,
            "versioned_id": "browser_source",
            "volume": 1.0
        },
        {
            "balance": 0.5,
            "deinterlace_field_order": 0,
            "deinterlace_mode": 0,
            "enabled": true,
            "flags": 0,
            "hotkeys": {
                "libobs.mute": [],
                "libobs.push-to-mute": [],
                "libobs.push-to-talk": [],
                "libobs.unmute": []
            },
            "id": "browser_source",
            "mixers": 255,
            "monitoring_type": 0,
            "muted": false,
            "name": "Navegador ET74C",
            "prev_ver": 436273153,
            "private_settings": {},
            "push-to-mute": false,
            "push-to-mute-delay": 0,
            "push-to-talk": false,
            "push-to-talk-delay": 0,
            "settings": {
                "height": 1080,
                "reroute_audio": true,
                "url": "https://moodleconf.ct.utfpr.edu.br/b/adr-oxu-3uq-0wx",
                "width": 1920
            },
            "sync": 0,
            "versioned_id": "browser_source",
            "volume": 1.0
        },
        {
            "balance": 0.5,
            "deinterlace_field_order": 0,
            "deinterlace_mode": 0,
            "enabled": true,
            "flags": 0,
            "hotkeys": {
                "libobs.mute": [],
                "libobs.push-to-mute": [],
                "libobs.push-to-talk": [],
                "libobs.unmute": []
            },
            "id": "browser_source",
            "mixers": 255,
            "monitoring_type": 0,
            "muted": false,
            "name": "Navegador ET52B",
            "prev_ver": 436273153,
            "private_settings": {},
            "push-to-mute": false,
            "push-to-mute-delay": 0,
            "push-to-talk": false,
            "push-to-talk-delay": 0,
            "settings": {
                "height": 1080,
                "reroute_audio": true,
                "url": "https://moodleconf.ct.utfpr.edu.br/b/adr-h9a-jdt-5ia",
                "width": 1920
            },
            "sync": 0,
            "versioned_id": "browser_source",
            "volume": 1.0
        },
        {
            "balance": 0.5,
            "deinterlace_field_order": 0,
            "deinterlace_mode": 0,
            "enabled": true,
            "flags": 0,
            "hotkeys": {},
            "id": "text_gdiplus",
            "mixers": 0,
            "monitoring_type": 0,
            "muted": false,
            "name": "Turma-ET52B",
            "prev_ver": 436273153,
            "private_settings": {},
            "push-to-mute": false,
            "push-to-mute-delay": 0,
            "push-to-talk": false,
            "push-to-talk-delay": 0,
            "settings": {
                "align": "center",
                "color": 4278190080,
                "font": {
                    "face": "Arial",
                    "flags": 0,
                    "size": 36,
                    "style": "Normal"
                },
                "text": "Turma N21"
            },
            "sync": 0,
            "versioned_id": "text_gdiplus_v2",
            "volume": 1.0
        },
        {
            "balance": 0.5,
            "deinterlace_field_order": 0,
            "deinterlace_mode": 0,
            "enabled": true,
            "flags": 0,
            "hotkeys": {},
            "id": "text_gdiplus",
            "mixers": 0,
            "monitoring_type": 0,
            "muted": false,
            "name": "Nome-ET52B",
            "prev_ver": 436273153,
            "private_settings": {},
            "push-to-mute": false,
            "push-to-mute-delay": 0,
            "push-to-talk": false,
            "push-to-talk-delay": 0,
            "settings": {
                "align": "center",
                "color": 4278190080,
                "font": {
                    "face": "Arial",
                    "flags": 0,
                    "size": 36,
                    "style": "Normal"
                },
                "text": "Eletrônica Analógica"
            },
            "sync": 0,
            "versioned_id": "text_gdiplus_v2",
            "volume": 1.0
        },
        {
            "balance": 0.5,
            "deinterlace_field_order": 0,
            "deinterlace_mode": 0,
            "enabled": true,
            "flags": 0,
            "hotkeys": {},
            "id": "text_gdiplus",
            "mixers": 0,
            "monitoring_type": 0,
            "muted": false,
            "name": "Nome-ET76C",
            "prev_ver": 436273153,
            "private_settings": {},
            "push-to-mute": false,
            "push-to-mute-delay": 0,
            "push-to-talk": false,
            "push-to-talk-delay": 0,
            "settings": {
                "align": "center",
                "color": 4278190080,
                "font": {
                    "face": "Arial",
                    "flags": 0,
                    "size": 48,
                    "style": "Normal"
                },
                "text": "Eletrônica de \nPotência"
            },
            "sync": 0,
            "versioned_id": "text_gdiplus_v2",
            "volume": 1.0
        },
        {
            "balance": 0.5,
            "deinterlace_field_order": 0,
            "deinterlace_mode": 0,
            "enabled": true,
            "flags": 0,
            "hotkeys": {},
            "id": "text_gdiplus",
            "mixers": 0,
            "monitoring_type": 0,
            "muted": false,
            "name": "Turmas-ET76C",
            "prev_ver": 436273153,
            "private_settings": {},
            "push-to-mute": false,
            "push-to-mute-delay": 0,
            "push-to-talk": false,
            "push-to-talk-delay": 0,
            "settings": {
                "align": "center",
                "color": 4278190080,
                "font": {
                    "face": "Arial",
                    "flags": 0,
                    "size": 36,
                    "style": "Normal"
                },
                "text": "Turma S25\n"
            },
            "sync": 0,
            "versioned_id": "text_gdiplus_v2",
            "volume": 1.0
        },
        {
            "balance": 0.5,
            "deinterlace_field_order": 0,
            "deinterlace_mode": 0,
            "enabled": true,
            "flags": 0,
            "hotkeys": {
                "libobs.mute": [],
                "libobs.push-to-mute": [],
                "libobs.push-to-talk": [],
                "libobs.unmute": []
            },
            "id": "browser_source",
            "mixers": 255,
            "monitoring_type": 0,
            "muted": false,
            "name": "Hora",
            "prev_ver": 436273153,
            "private_settings": {},
            "push-to-mute": false,
            "push-to-mute-delay": 0,
            "push-to-talk": false,
            "push-to-talk-delay": 0,
            "settings": {
                "url": "https://time.is/"
            },
            "sync": 0,
            "versioned_id": "browser_source",
            "volume": 1.0
        }
    ],
    "transition_duration": 450,
    "transitions": []
}